{
    "station":
    [
     {
     "name": "Otvoreni LIVE",
     "streamURL": "https://stream.otvoreni.hr/stream48",
     "imageURL": "https://www.otvoreni.hr/ea/wp-content/uploads/2019/06/cover_live.png",
     "desc": "",
     "longDesc": ""
     },
     {
     "name": "Otvoreni HO-HO",
     "streamURL": "https://stream.otvoreni.hr:443/hoho",
     "imageURL": "https://www.otvoreni.hr/ea/wp-content/uploads/2019/06/cover_hoho.png",
     "desc": "",
     "longDesc": ""
     },
     {
     "name": "Otvoreni Love",
     "streamURL": "https://stream.otvoreni.hr:443/love",
     "imageURL": "https://www.otvoreni.hr/ea/wp-content/uploads/2020/01/cover_love.jpg",
     "desc": "",
     "longDesc": ""
     },
     {
     "name": "Otvoreni Fitness",
     "streamURL": "https://stream.otvoreni.hr:443/fitness",
     "imageURL":"https://www.otvoreni.hr/ea/wp-content/uploads/2019/06/cover_fitness.png",
     "desc": "",
     "longDesc": ""
     },
     {
     "name": "Otvoreni Chill",
     "streamURL": "https://stream.otvoreni.hr:443/chill",
     "imageURL": "https://www.otvoreni.hr/ea/wp-content/uploads/2019/06/cover_chill.png",
     "desc": "",
     "longDesc": ""
     },
     {
     "name": "Yammat FM (Mirna 👑)",
     "streamURL": "https://streaming.radio.co/s5ad4b474a/listen",
     "imageURL": "https://cdn.onlineradiobox.com/img/l/6/24776.v8.png",
     "desc": "",
     "longDesc": ""
     }
    ]
}
